scramblepdf/__init__.py
scramblepdf/__main__.py
scramblepdf/cli.py
scramblepdf-0.3.4.dist-info/LICENSE
scramblepdf-0.3.4.dist-info/METADATA
scramblepdf-0.3.4.dist-info/WHEEL
scramblepdf-0.3.4.dist-info/entry_points.txt
scramblepdf-0.3.4.dist-info/RECORD
