Metadata-Version: 2.3
Name: scramblepdf
Version: 0.3.4
Summary: 
License: MIT
Keywords: utilities
Author: VermiIIi0n
Author-email: dungeon.behind0t@icloud.com
Requires-Python: >=3.12,<4.0
Classifier: Development Status :: 4 - Beta
Classifier: Framework :: Pytest
Classifier: Intended Audience :: Developers
Classifier: License :: OSI Approved :: MIT License
Classifier: Operating System :: OS Independent
Classifier: Programming Language :: Python :: 3
Classifier: Programming Language :: Python :: 3.12
Classifier: Programming Language :: Python :: 3.13
Classifier: Programming Language :: Python :: Implementation :: CPython
Classifier: Programming Language :: Python :: Implementation :: PyPy
Classifier: Topic :: Utilities
Classifier: Typing :: Typed
Provides-Extra: webui
Requires-Dist: fonttools (>=4.57.0,<5.0.0)
Requires-Dist: pikepdf (>=9.7.0,<10.0.0)
Project-URL: Homepage, https://github.com/VermiIIi0n/scramble-pdf
Project-URL: Issues, https://github.com/VermiIIi0n/scramble-pdf/issues
